fastapi_framework_mvc/__init__.py
fastapi_framework_mvc/app.py
fastapi_framework_mvc/azure.py
fastapi_framework_mvc/cli.py
fastapi_framework_mvc/server.py
fastapi_framework_mvc/wsgi.py
fastapi_framework_mvc/Config/__init__.py
fastapi_framework_mvc/Config/config.py
fastapi_framework_mvc/Config/json.py
fastapi_framework_mvc/Config/yaml.py
fastapi_framework_mvc/Controllers/__init__.py
fastapi_framework_mvc/Controllers/WS/__init__.py
fastapi_framework_mvc/Controllers/Web/HTTP40XController.py
fastapi_framework_mvc/Controllers/Web/HTTP50XController.py
fastapi_framework_mvc/Controllers/Web/__init__.py
fastapi_framework_mvc/Database/__init__.py
fastapi_framework_mvc/Database/decorators.py
fastapi_framework_mvc/Database/driver.py
fastapi_framework_mvc/Deprecation/__init__.py
fastapi_framework_mvc/Exceptions/ConfigExceptions.py
fastapi_framework_mvc/Exceptions/QueryExceptions.py
fastapi_framework_mvc/Exceptions/RuntimeExceptions.py
fastapi_framework_mvc/Exceptions/__init__.py
fastapi_framework_mvc/Libs/__init__.py
fastapi_framework_mvc/Libs/decorator.py
fastapi_framework_mvc/Server/ErrorHandler.py
fastapi_framework_mvc/Server/Middleware.py
fastapi_framework_mvc/Server/Plugins.py
fastapi_framework_mvc/Server/Socket.py
fastapi_framework_mvc/Server/WS.py
fastapi_framework_mvc/Server/Web.py
fastapi_framework_mvc/Server/__init__.py
fastapi_framework_mvc/Task/__init__.py
fastapi_framework_mvc/Utils/__init__.py
fastapi_framework_mvc/Utils/module.py
fastapi_framework_mvc/Utils/templates.py
fastapi_framework_mvc/Utils/utils.py
fastapi_framework_mvc/Utils/Auth/__init__.py
fastapi_framework_mvc/Utils/Auth/decorators.py
fastapi_framework_mvc/static/favicon.ico
fastapi_framework_mvc/static/css/app.css
fastapi_framework_mvc/static/css/app.csse
fastapi_framework_mvc/static/css/style.css
fastapi_framework_mvc/templates/404.html
fastapi_framework_mvc/templates/500.html
fastapi_framework_mvc/templates/welcome.html
fastapi_framework_mvc/templates/layout/app.html
fastapi_framework_mvc-1.1.16.dist-info/licenses/LICENSE
fastapi_framework_mvc-1.1.16.dist-info/METADATA
fastapi_framework_mvc-1.1.16.dist-info/WHEEL
fastapi_framework_mvc-1.1.16.dist-info/entry_points.txt
fastapi_framework_mvc-1.1.16.dist-info/top_level.txt
fastapi_framework_mvc-1.1.16.dist-info/RECORD
