Metadata-Version: 2.4
Name: fastapi-framework-mvc
Version: 1.1.16
Summary: FastAPI MVC framework
Author-email: Frédérick NEY <frederick.ney@gmail.com>
License:                     GNU GENERAL PUBLIC LICENSE
Project-URL: Homepage, https://github.com/frederickney/fastapi-framework-mvc
Project-URL: Documentation, https://github.com/frederickney/fastapi-framework-mvc/blob/master/readme.md
Project-URL: Repository, https://github.com/frederickney/fastapi-framework-mvc
Project-URL: Issues, https://github.com/frederickney/fastapi-framework-mvc/issues
Project-URL: source, https://github.com/frederickney/fastapi-framework-mvc
Classifier: Environment :: Web Environment
Classifier: Intended Audience :: Developers
Classifier: Operating System :: OS Independent
Classifier: Framework :: FastAPI
Classifier: Topic :: Software Development :: Libraries :: Python Modules
Classifier: Programming Language :: Python :: 3.7
Classifier: Programming Language :: Python :: 3.8
Classifier: Programming Language :: Python :: 3.9
Classifier: Programming Language :: Python :: 3.10
Classifier: Programming Language :: Python :: 3.11
Classifier: Programming Language :: Python :: 3.12
Classifier: Programming Language :: Python :: 3.13
Requires-Python: >=3.7
License-File: LICENSE
Requires-Dist: six
Requires-Dist: jinja2
Requires-Dist: requests
Requires-Dist: urllib3
Requires-Dist: gunicorn
Requires-Dist: uvicorn
Requires-Dist: pyyaml
Requires-Dist: pyopenssl
Requires-Dist: SQLAlchemy
Requires-Dist: tornado
Requires-Dist: FastAPI
Requires-Dist: importlib-metadata; python_version > "3.7"
Dynamic: license-file
